pydork/__init__.py
pydork/common.py
pydork/engine.py
pydork/engine_baidu.py
pydork/engine_bing.py
pydork/engine_common.py
pydork/engine_duckduckgo.py
pydork/engine_google.py
pydork/engine_yahoo.py
pydork/engine_yandex.py
pydork/messages.py
pydork/recaptcha.py
pydork/sub_commands.py
pydork/subcommands.py
pydork/test_engine.py
pydork/test_engine_selenium.py
pydork-1.1.7.data/data/etc/bash_completion.d/pydork-completion.bash
pydork-1.1.7.data/data/share/zsh/site-functions/_pydork
pydork-1.1.7.data/data/share/zsh/site-functions/pydork-completion.bash
pydork-1.1.7.dist-info/LICENSE
pydork-1.1.7.dist-info/METADATA
pydork-1.1.7.dist-info/WHEEL
pydork-1.1.7.dist-info/entry_points.txt
pydork-1.1.7.dist-info/top_level.txt
pydork-1.1.7.dist-info/RECORD
