Metadata-Version: 2.1
Name: pydork
Version: 1.1.7
Summary: Scraping and listing text and image searches on Google, Bing, DuckDuckGo, Baidu, Yahoo japan.
Home-page: https://github.com/blacknon/pydork
Author: blacknon
Author-email: blacknon@orebibou.com
Maintainer: blacknon
Maintainer-email: blacknon@orebibou.com
License: MIT License
Classifier: Programming Language :: Python :: 3
Classifier: Programming Language :: Python :: 3.7
Classifier: Programming Language :: Python :: 3.8
Classifier: Programming Language :: Python :: 3.9
Classifier: Programming Language :: Python :: 3.10
Classifier: Programming Language :: Python :: 3.11
Classifier: License :: OSI Approved :: MIT License
License-File: LICENSE
Requires-Dist: bs4
Requires-Dist: get-chrome-driver
Requires-Dist: get-gecko-driver
Requires-Dist: chromedriver-autoinstaller
Requires-Dist: geckodriver-autoinstaller
Requires-Dist: fake-useragent
Requires-Dist: lxml
Requires-Dist: requests[socks]
Requires-Dist: selenium ==4.7.2
Requires-Dist: selenium-requests
Requires-Dist: pickle-mixin
Requires-Dist: sphinx
Requires-Dist: sphinx-rtd-theme
Requires-Dist: sphinx-autobuild
